git_rag_embedder/__init__.py
git_rag_embedder/chunker.py
git_rag_embedder/core.py
git_rag_embedder/embeddings.py
git_rag_embedder/file_processor.py
git_rag_embedder/repository_loader.py
git_rag_embedder/serializer.py
git_rag_embedder-0.1.1.dist-info/METADATA
git_rag_embedder-0.1.1.dist-info/WHEEL
git_rag_embedder-0.1.1.dist-info/top_level.txt
git_rag_embedder-0.1.1.dist-info/RECORD
