Metadata-Version: 2.4
Name: git-rag-embedder
Version: 0.1.1
Summary: Minimalist library to convert Git repositories and local directories into embeddings
Author-email: Artur Gromenkov <your.email@example.com>
Requires-Python: >=3.8
Requires-Dist: requests>=2.25.0
Requires-Dist: tiktoken>=0.4.0
Requires-Dist: numpy>=1.21.0
Requires-Dist: python-dotenv>=0.19.0
Requires-Dist: sentence-transformers>=2.2.0
Requires-Dist: transformers>=4.20.0
Requires-Dist: torch>=1.9.0
Provides-Extra: openai
Requires-Dist: openai>=1.0.0; extra == "openai"
Provides-Extra: dev
Requires-Dist: pytest>=6.0; extra == "dev"
Requires-Dist: black>=21.0; extra == "dev"
Requires-Dist: isort>=5.0; extra == "dev"
